paqprueba/__init__.py
paqprueba/common.py
paqprueba/paqprueba.py
paqprueba-0.0.2.dist-info/LICENSE
paqprueba-0.0.2.dist-info/METADATA
paqprueba-0.0.2.dist-info/WHEEL
paqprueba-0.0.2.dist-info/entry_points.txt
paqprueba-0.0.2.dist-info/top_level.txt
paqprueba-0.0.2.dist-info/RECORD
