Metadata-Version: 2.1
Name: paqprueba
Version: 0.0.2
Summary: un paquete de python de prueba
Author-email: Evelyn Tengler <tenglerevelyn@gmail.com>
License: MIT License
Project-URL: Homepage, https://github.com/etengler/paqprueba
Keywords: paqprueba
Classifier: Intended Audience :: Developers
Classifier: License :: OSI Approved :: MIT License
Classifier: Natural Language :: English
Classifier: Programming Language :: Python :: 3.8
Classifier: Programming Language :: Python :: 3.9
Classifier: Programming Language :: Python :: 3.10
Classifier: Programming Language :: Python :: 3.11
Classifier: Programming Language :: Python :: 3.12
Requires-Python: >=3.8
License-File: LICENSE
Requires-Dist: numpy
Provides-Extra: all
Requires-Dist: paqprueba[extra] ; extra == 'all'
Provides-Extra: extra
Requires-Dist: pandas ; extra == 'extra'
